jfjson/__init__.py
jfjson/core.py
jfjson/py.typed
jfjson-0.0.3.dist-info/LICENSE
jfjson-0.0.3.dist-info/METADATA
jfjson-0.0.3.dist-info/WHEEL
jfjson-0.0.3.dist-info/top_level.txt
jfjson-0.0.3.dist-info/RECORD
