Metadata-Version: 2.1
Name: jfjson
Version: 0.0.3
Summary: Automatic json parsing and serialing
Home-page: https://github.com/tyehle/jfjson
Author: Tobin Yehle
Author-email: tobin@yehle.us
License: UNKNOWN
Platform: UNKNOWN
Classifier: Development Status :: 4 - Beta
Classifier: License :: OSI Approved :: MIT License
Classifier: Programming Language :: Python :: 3
Classifier: Programming Language :: Python :: 3.7
Classifier: Programming Language :: Python :: 3.8
Classifier: Programming Language :: Python :: 3.9
Classifier: Operating System :: OS Independent
Classifier: Topic :: Software Development
Classifier: Intended Audience :: Developers
Classifier: Typing :: Typed
